fnli/__init__.py
fnli/datasets/__init__.py
fnli/datasets/fnli.py
fnli/preprocessing/__init__.py
fnli/preprocessing/k_sequence.py
fnli/preprocessing/sequence.py
fnli/utils/__init__.py
fnli/utils/data_utils.py
fnli/utils/generic_utils.py
fnli-1.0.1.dist-info/LICENSE
fnli-1.0.1.dist-info/METADATA
fnli-1.0.1.dist-info/WHEEL
fnli-1.0.1.dist-info/top_level.txt
fnli-1.0.1.dist-info/RECORD
