Metadata-Version: 2.1
Name: fnli
Version: 1.0.1
Summary: persian Natural Language Inference dataset
Home-page: https://github.com/m-azari/fnli
Author: mohammad azari jafari
Author-email: azari.jafari.m@gmail.com
License: UNKNOWN
Platform: UNKNOWN
Classifier: Programming Language :: Python :: 3
Classifier: License :: OSI Approved :: MIT License
Classifier: Operating System :: OS Independent
Classifier: Natural Language :: Persian
Requires-Python: >=3.6
